holoviz_mcp/__init__.py
holoviz_mcp/cli.py
holoviz_mcp/client.py
holoviz_mcp/py.typed
holoviz_mcp/serve.py
holoviz_mcp/server.py
holoviz_mcp/apps/__init__.py
holoviz_mcp/apps/configuration_viewer.py
holoviz_mcp/apps/holoviews_get_docstring.py
holoviz_mcp/apps/holoviz_get_skill.py
holoviz_mcp/apps/holoviz_search.py
holoviz_mcp/apps/hvplot_get_docstring.py
holoviz_mcp/apps/hvplot_get_signature.py
holoviz_mcp/apps/hvplot_list_plot_types.py
holoviz_mcp/apps/panel_get_component.py
holoviz_mcp/apps/panel_get_component_parameters.py
holoviz_mcp/apps/panel_list_components.py
holoviz_mcp/apps/panel_list_packages.py
holoviz_mcp/apps/panel_search_components.py
holoviz_mcp/config/__init__.py
holoviz_mcp/config/config.yaml
holoviz_mcp/config/loader.py
holoviz_mcp/config/models.py
holoviz_mcp/config/schema.json
holoviz_mcp/config/resources/agents/claude/holoviz-app-architect.md
holoviz_mcp/config/resources/agents/claude/holoviz-data-explorer.md
holoviz_mcp/config/resources/agents/copilot/holoviz-app-architect.agent.md
holoviz_mcp/config/resources/agents/copilot/holoviz-data-explorer.agent.md
holoviz_mcp/config/resources/skills/holoviews.md
holoviz_mcp/config/resources/skills/hvplot.md
holoviz_mcp/config/resources/skills/panel-custom-components.md
holoviz_mcp/config/resources/skills/panel-material-ui.md
holoviz_mcp/config/resources/skills/panel.md
holoviz_mcp/config/resources/skills/param.md
holoviz_mcp/display_mcp/__init__.py
holoviz_mcp/display_mcp/app.py
holoviz_mcp/display_mcp/cli.py
holoviz_mcp/display_mcp/client.py
holoviz_mcp/display_mcp/database.py
holoviz_mcp/display_mcp/endpoints.py
holoviz_mcp/display_mcp/manager.py
holoviz_mcp/display_mcp/ui.py
holoviz_mcp/display_mcp/utils.py
holoviz_mcp/display_mcp/pages/__init__.py
holoviz_mcp/display_mcp/pages/add_page.py
holoviz_mcp/display_mcp/pages/admin_page.py
holoviz_mcp/display_mcp/pages/feed_page.py
holoviz_mcp/display_mcp/pages/view_page.py
holoviz_mcp/holoviews_mcp/__init__.py
holoviz_mcp/holoviews_mcp/server.py
holoviz_mcp-0.14.5.dist-info/METADATA
holoviz_mcp-0.14.5.dist-info/WHEEL
holoviz_mcp-0.14.5.dist-info/entry_points.txt
holoviz_mcp-0.14.5.dist-info/licenses/LICENSE.txt
holoviz_mcp-0.14.5.dist-info/RECORD
