Metadata-Version: 2.4
Name: holoviz-mcp
Version: 0.14.5
Summary: A Model Context Protocol (MCP) server for the HoloViz ecosystem
Project-URL: Homepage, https://github.com/MarcSkovMadsen/holoviz-mcp
Project-URL: Source, https://github.com/MarcSkovMadsen/holoviz-mcp
Author-email: MarcSkovMadsen <marc.skov.madsen@gmail.com>
Maintainer-email: MarcSkovMadsen <marc.skov.madsen@gmail.com>
License: BSD
License-File: LICENSE.txt
Classifier: Development Status :: 5 - Production/Stable
Classifier: Intended Audience :: Developers
Classifier: Intended Audience :: Science/Research
Classifier: License :: OSI Approved :: BSD License
Classifier: Natural Language :: English
Classifier: Operating System :: OS Independent
Classifier: Programming Language :: Python :: 3
Classifier: Programming Language :: Python :: 3.11
Classifier: Programming Language :: Python :: 3.12
Classifier: Programming Language :: Python :: 3.13
Classifier: Topic :: Scientific/Engineering
Classifier: Topic :: Software Development :: Libraries
Requires-Python: >=3.11
Requires-Dist: certifi
Requires-Dist: chromadb
Requires-Dist: fastmcp<3
Requires-Dist: gitpython
Requires-Dist: hvplot
Requires-Dist: hvsampledata
Requires-Dist: matplotlib
Requires-Dist: nbconvert
Requires-Dist: packaging
Requires-Dist: panel
Requires-Dist: panel-full-calendar
Requires-Dist: panel-graphic-walker
Requires-Dist: panel-material-ui
Requires-Dist: panel-neuroglancer
Requires-Dist: panel-precision-slider
Requires-Dist: panel-splitjs
Requires-Dist: panel-web-llm
Requires-Dist: playwright
Requires-Dist: plotly
Requires-Dist: pydantic>=2.0
Requires-Dist: pyyaml
Requires-Dist: requests
Requires-Dist: typer
Requires-Dist: watchfiles
Provides-Extra: dev
Requires-Dist: ipykernel; extra == 'dev'
Requires-Dist: mkdocs; extra == 'dev'
Requires-Dist: mkdocs-material; extra == 'dev'
Requires-Dist: mkdocs-pycafe; extra == 'dev'
Requires-Dist: mkdocstrings[python]; extra == 'dev'
Requires-Dist: pre-commit; extra == 'dev'
Requires-Dist: pytest; extra == 'dev'
Requires-Dist: pytest-asyncio; extra == 'dev'
Requires-Dist: pytest-rerunfailures; extra == 'dev'
Requires-Dist: pytest-xdist; extra == 'dev'
Requires-Dist: types-pyyaml; extra == 'dev'
Provides-Extra: mypy
Requires-Dist: mypy; extra == 'mypy'
Requires-Dist: types-requests; extra == 'mypy'
Requires-Dist: typing-extensions; extra == 'mypy'
Provides-Extra: pydata
Requires-Dist: altair; extra == 'pydata'
Requires-Dist: duckdb; extra == 'pydata'
Requires-Dist: polars; extra == 'pydata'
Requires-Dist: pytest; extra == 'pydata'
Requires-Dist: scikit-learn; extra == 'pydata'
Requires-Dist: seaborn; extra == 'pydata'
Requires-Dist: vega-datasets; extra == 'pydata'
Requires-Dist: yfinance; extra == 'pydata'
